{
  "generated_at": "2026-05-05T01:40:56.632Z",
  "repository": "kitsuyui/ts-playground",
  "default_branch": "main",
  "publish_branch": "gh-counter-assets",
  "event_name": "push",
  "base_reference": "2732ad82ff8b4657b24e37419930de5933bf60b8",
  "head_reference": "8da56e2093cc55c7add1e3a7c53b19f96f1d5104",
  "bootstrap_message": null,
  "counters": [
    {
      "id": "maintenance-comments",
      "label": "TODO/FIXME",
      "current": 2,
      "base": 2,
      "delta": 0,
      "commentable": true,
      "touched_files": [],
      "violations": [],
      "badge_path": ".gh-counter/badges/maintenance-comments.svg",
      "counter_path": ".gh-counter/counters/maintenance-comments.json"
    }
  ]
}
